stringimporter/__init__.py
stringimporter-0.1.4.dist-info/DESCRIPTION.rst
stringimporter-0.1.4.dist-info/METADATA
stringimporter-0.1.4.dist-info/RECORD
stringimporter-0.1.4.dist-info/WHEEL
stringimporter-0.1.4.dist-info/metadata.json
stringimporter-0.1.4.dist-info/top_level.txt
