Metadata-Version: 2.0
Name: stringimporter
Version: 0.1.4
Summary: Arbitrary import Python source as a Python module
Home-page: https://github.com/majerteam/stringimporter
Author: Feth Arezki
Author-email: tech@majerti.fr
License: UNKNOWN
Download-URL: https://github.com/majerteam/stringimporter
Platform: UNKNOWN
